{
  "source_L1": "L1_q440_min5_pool_ac89fa8d",
  "generated_at": "2025-12-02 16:16:13",
  "start_date": "2025-07-27",
  "end_date": "2025-10-15",
  "roles": {
    "TOP": {
      "Banshee": {
        "games": 17,
        "avg_damage": 135459.41,
        "avg_damage_taken": 22054.18,
        "avg_gold": 10245.53,
        "avg_farm": 199.41,
        "avg_vision": 16.53,
        "avg_turret_damage": 2043.06,
        "avg_kills": 2.76,
        "avg_deaths": 5.18,
        "avg_assists": 3.82,
        "avg_kill_participation": 25.36,
        "winrate": 47.06
      },
      "TheChosenUndead": {
        "games": 25,
        "avg_damage": 137198.88,
        "avg_damage_taken": 29860.2,
        "avg_gold": 11055.6,
        "avg_farm": 168.52,
        "avg_vision": 20.28,
        "avg_turret_damage": 2402.44,
        "avg_kills": 4.84,
        "avg_deaths": 6.64,
        "avg_assists": 4.92,
        "avg_kill_participation": 31.72,
        "winrate": 52.0
      },
      "Kyoraku": {
        "games": 52,
        "avg_damage": 174492.15,
        "avg_damage_taken": 33142.9,
        "avg_gold": 13522.46,
        "avg_farm": 212.13,
        "avg_vision": 18.6,
        "avg_turret_damage": 7386.52,
        "avg_kills": 7.25,
        "avg_deaths": 4.33,
        "avg_assists": 5.94,
        "avg_kill_participation": 44.84,
        "winrate": 61.54
      },
      "SN Bin": {
        "games": 47,
        "avg_damage": 168237.23,
        "avg_damage_taken": 35713.28,
        "avg_gold": 12530.83,
        "avg_farm": 202.45,
        "avg_vision": 14.53,
        "avg_turret_damage": 4908.62,
        "avg_kills": 6.17,
        "avg_deaths": 5.23,
        "avg_assists": 6.68,
        "avg_kill_participation": 44.88,
        "winrate": 48.94
      },
      "Dexus": {
        "games": 8,
        "avg_damage": 131831.0,
        "avg_damage_taken": 23032.0,
        "avg_gold": 9726.88,
        "avg_farm": 149.75,
        "avg_vision": 14.62,
        "avg_turret_damage": 5355.75,
        "avg_kills": 4.5,
        "avg_deaths": 5.88,
        "avg_assists": 4.12,
        "avg_kill_participation": 33.28,
        "winrate": 25.0
      },
      "maibad": {
        "games": 23,
        "avg_damage": 159251.57,
        "avg_damage_taken": 33332.13,
        "avg_gold": 12780.96,
        "avg_farm": 186.3,
        "avg_vision": 17.17,
        "avg_turret_damage": 3431.91,
        "avg_kills": 7.39,
        "avg_deaths": 5.91,
        "avg_assists": 7.3,
        "avg_kill_participation": 45.06,
        "winrate": 43.48
      },
      "Bustamantefanboy": {
        "games": 58,
        "avg_damage": 165037.66,
        "avg_damage_taken": 33172.55,
        "avg_gold": 12337.93,
        "avg_farm": 211.76,
        "avg_vision": 14.86,
        "avg_turret_damage": 4528.98,
        "avg_kills": 5.24,
        "avg_deaths": 4.88,
        "avg_assists": 5.41,
        "avg_kill_participation": 38.39,
        "winrate": 46.55
      },
      "Joseph Joestar": {
        "games": 18,
        "avg_damage": 158389.33,
        "avg_damage_taken": 30550.0,
        "avg_gold": 11478.44,
        "avg_farm": 203.5,
        "avg_vision": 18.06,
        "avg_turret_damage": 4321.56,
        "avg_kills": 3.17,
        "avg_deaths": 6.06,
        "avg_assists": 5.83,
        "avg_kill_participation": 34.91,
        "winrate": 33.33
      },
      "En Vlc No F0II0": {
        "games": 8,
        "avg_damage": 182729.5,
        "avg_damage_taken": 49872.5,
        "avg_gold": 13215.0,
        "avg_farm": 206.75,
        "avg_vision": 23.5,
        "avg_turret_damage": 6563.62,
        "avg_kills": 5.25,
        "avg_deaths": 6.25,
        "avg_assists": 7.75,
        "avg_kill_participation": 39.42,
        "winrate": 37.5
      },
      "FUSHROHDAH": {
        "games": 8,
        "avg_damage": 160109.38,
        "avg_damage_taken": 42023.88,
        "avg_gold": 13298.12,
        "avg_farm": 192.5,
        "avg_vision": 20.62,
        "avg_turret_damage": 5661.5,
        "avg_kills": 5.0,
        "avg_deaths": 4.25,
        "avg_assists": 11.25,
        "avg_kill_participation": 48.31,
        "winrate": 62.5
      },
      "Frieren": {
        "games": 3,
        "avg_damage": 124109.67,
        "avg_damage_taken": 28064.67,
        "avg_gold": 10920.67,
        "avg_farm": 175.67,
        "avg_vision": 17.0,
        "avg_turret_damage": 6295.67,
        "avg_kills": 4.67,
        "avg_deaths": 4.33,
        "avg_assists": 5.67,
        "avg_kill_participation": 41.68,
        "winrate": 66.67
      },
      "Morocha": {
        "games": 3,
        "avg_damage": 113500.67,
        "avg_damage_taken": 37297.0,
        "avg_gold": 9816.67,
        "avg_farm": 152.0,
        "avg_vision": 14.0,
        "avg_turret_damage": 3310.67,
        "avg_kills": 5.0,
        "avg_deaths": 8.33,
        "avg_assists": 3.67,
        "avg_kill_participation": 17.97,
        "winrate": 33.33
      },
      "Nikken": {
        "games": 4,
        "avg_damage": 143627.5,
        "avg_damage_taken": 26420.75,
        "avg_gold": 11182.25,
        "avg_farm": 202.5,
        "avg_vision": 17.0,
        "avg_turret_damage": 4184.0,
        "avg_kills": 2.75,
        "avg_deaths": 2.25,
        "avg_assists": 5.25,
        "avg_kill_participation": 36.02,
        "winrate": 50.0
      },
      "Däzzler": {
        "games": 3,
        "avg_damage": 112619.33,
        "avg_damage_taken": 22797.0,
        "avg_gold": 9963.0,
        "avg_farm": 151.33,
        "avg_vision": 15.0,
        "avg_turret_damage": 5594.67,
        "avg_kills": 3.67,
        "avg_deaths": 2.67,
        "avg_assists": 10.67,
        "avg_kill_participation": 37.06,
        "winrate": 66.67
      }
    },
    "JUNGLE": {
      "Joseph Joestar": {
        "games": 27,
        "avg_damage": 218666.37,
        "avg_damage_taken": 39229.33,
        "avg_gold": 11514.22,
        "avg_farm": 14.81,
        "avg_vision": 23.7,
        "avg_turret_damage": 1317.19,
        "avg_kills": 5.59,
        "avg_deaths": 5.59,
        "avg_assists": 9.59,
        "avg_kill_participation": 48.31,
        "winrate": 59.26
      },
      "Kyoraku": {
        "games": 27,
        "avg_damage": 253618.67,
        "avg_damage_taken": 46802.37,
        "avg_gold": 13964.48,
        "avg_farm": 29.15,
        "avg_vision": 23.74,
        "avg_turret_damage": 1641.33,
        "avg_kills": 9.81,
        "avg_deaths": 5.37,
        "avg_assists": 11.48,
        "avg_kill_participation": 64.76,
        "winrate": 48.15
      },
      "Dexus": {
        "games": 81,
        "avg_damage": 282871.36,
        "avg_damage_taken": 41184.9,
        "avg_gold": 14210.93,
        "avg_farm": 22.9,
        "avg_vision": 20.46,
        "avg_turret_damage": 3071.67,
        "avg_kills": 9.37,
        "avg_deaths": 5.69,
        "avg_assists": 7.69,
        "avg_kill_participation": 63.68,
        "winrate": 46.91
      },
      "SN Bin": {
        "games": 14,
        "avg_damage": 244923.5,
        "avg_damage_taken": 41856.43,
        "avg_gold": 12525.57,
        "avg_farm": 24.0,
        "avg_vision": 27.57,
        "avg_turret_damage": 1588.29,
        "avg_kills": 6.0,
        "avg_deaths": 6.07,
        "avg_assists": 12.86,
        "avg_kill_participation": 61.25,
        "winrate": 50.0
      },
      "En Vlc No F0II0": {
        "games": 24,
        "avg_damage": 221262.71,
        "avg_damage_taken": 36391.29,
        "avg_gold": 10742.83,
        "avg_farm": 17.62,
        "avg_vision": 21.88,
        "avg_turret_damage": 1013.42,
        "avg_kills": 3.92,
        "avg_deaths": 5.83,
        "avg_assists": 10.08,
        "avg_kill_participation": 50.94,
        "winrate": 54.17
      },
      "maibad": {
        "games": 17,
        "avg_damage": 234058.53,
        "avg_damage_taken": 40546.88,
        "avg_gold": 12665.29,
        "avg_farm": 18.47,
        "avg_vision": 17.12,
        "avg_turret_damage": 818.35,
        "avg_kills": 8.47,
        "avg_deaths": 5.88,
        "avg_assists": 10.65,
        "avg_kill_participation": 63.55,
        "winrate": 52.94
      },
      "FUSHROHDAH": {
        "games": 14,
        "avg_damage": 194213.36,
        "avg_damage_taken": 35777.36,
        "avg_gold": 10001.57,
        "avg_farm": 19.5,
        "avg_vision": 22.14,
        "avg_turret_damage": 327.07,
        "avg_kills": 4.57,
        "avg_deaths": 6.43,
        "avg_assists": 6.64,
        "avg_kill_participation": 50.08,
        "winrate": 14.29
      },
      "Bustamantefanboy": {
        "games": 40,
        "avg_damage": 220778.4,
        "avg_damage_taken": 33082.32,
        "avg_gold": 11506.33,
        "avg_farm": 16.07,
        "avg_vision": 20.23,
        "avg_turret_damage": 1569.7,
        "avg_kills": 6.35,
        "avg_deaths": 4.42,
        "avg_assists": 10.32,
        "avg_kill_participation": 57.58,
        "winrate": 50.0
      },
      "Frieren": {
        "games": 29,
        "avg_damage": 195375.31,
        "avg_damage_taken": 38962.66,
        "avg_gold": 11339.31,
        "avg_farm": 17.86,
        "avg_vision": 30.07,
        "avg_turret_damage": 1290.62,
        "avg_kills": 5.86,
        "avg_deaths": 5.21,
        "avg_assists": 11.9,
        "avg_kill_participation": 55.04,
        "winrate": 55.17
      },
      "Banshee": {
        "games": 1,
        "avg_damage": 230943.0,
        "avg_damage_taken": 43975.0,
        "avg_gold": 10700.0,
        "avg_farm": 31.0,
        "avg_vision": 21.0,
        "avg_turret_damage": 0.0,
        "avg_kills": 1.0,
        "avg_deaths": 9.0,
        "avg_assists": 13.0,
        "avg_kill_participation": 35.9,
        "winrate": 0.0
      },
      "Däzzler": {
        "games": 2,
        "avg_damage": 212821.5,
        "avg_damage_taken": 30935.5,
        "avg_gold": 12935.5,
        "avg_farm": 14.5,
        "avg_vision": 27.5,
        "avg_turret_damage": 1833.0,
        "avg_kills": 10.0,
        "avg_deaths": 2.5,
        "avg_assists": 7.5,
        "avg_kill_participation": 43.84,
        "winrate": 100.0
      },
      "TheChosenUndead": {
        "games": 1,
        "avg_damage": 289990.0,
        "avg_damage_taken": 39503.0,
        "avg_gold": 14840.0,
        "avg_farm": 15.0,
        "avg_vision": 22.0,
        "avg_turret_damage": 0.0,
        "avg_kills": 14.0,
        "avg_deaths": 9.0,
        "avg_assists": 2.0,
        "avg_kill_participation": 53.33,
        "winrate": 0.0
      }
    },
    "MIDDLE": {
      "SN Bin": {
        "games": 22,
        "avg_damage": 169264.55,
        "avg_damage_taken": 28635.82,
        "avg_gold": 13119.41,
        "avg_farm": 206.05,
        "avg_vision": 18.32,
        "avg_turret_damage": 3217.45,
        "avg_kills": 7.32,
        "avg_deaths": 6.36,
        "avg_assists": 8.55,
        "avg_kill_participation": 50.56,
        "winrate": 45.45
      },
      "Bustamantefanboy": {
        "games": 42,
        "avg_damage": 167262.24,
        "avg_damage_taken": 23121.69,
        "avg_gold": 12108.33,
        "avg_farm": 207.31,
        "avg_vision": 15.9,
        "avg_turret_damage": 3705.93,
        "avg_kills": 5.48,
        "avg_deaths": 5.48,
        "avg_assists": 7.31,
        "avg_kill_participation": 42.93,
        "winrate": 47.62
      },
      "Banshee": {
        "games": 44,
        "avg_damage": 178277.64,
        "avg_damage_taken": 24283.89,
        "avg_gold": 13056.25,
        "avg_farm": 227.34,
        "avg_vision": 23.59,
        "avg_turret_damage": 2232.52,
        "avg_kills": 5.61,
        "avg_deaths": 5.09,
        "avg_assists": 6.89,
        "avg_kill_participation": 43.23,
        "winrate": 29.55
      },
      "Kyoraku": {
        "games": 24,
        "avg_damage": 164246.12,
        "avg_damage_taken": 23840.0,
        "avg_gold": 12690.54,
        "avg_farm": 207.54,
        "avg_vision": 19.33,
        "avg_turret_damage": 5074.96,
        "avg_kills": 7.54,
        "avg_deaths": 4.38,
        "avg_assists": 6.5,
        "avg_kill_participation": 49.37,
        "winrate": 41.67
      },
      "Joseph Joestar": {
        "games": 27,
        "avg_damage": 140699.19,
        "avg_damage_taken": 20397.48,
        "avg_gold": 11504.81,
        "avg_farm": 182.44,
        "avg_vision": 17.56,
        "avg_turret_damage": 2960.7,
        "avg_kills": 4.78,
        "avg_deaths": 4.7,
        "avg_assists": 8.07,
        "avg_kill_participation": 42.51,
        "winrate": 70.37
      },
      "Frieren": {
        "games": 40,
        "avg_damage": 171093.88,
        "avg_damage_taken": 21829.75,
        "avg_gold": 13312.88,
        "avg_farm": 215.12,
        "avg_vision": 28.27,
        "avg_turret_damage": 3374.03,
        "avg_kills": 7.7,
        "avg_deaths": 4.0,
        "avg_assists": 9.47,
        "avg_kill_participation": 51.9,
        "winrate": 67.5
      },
      "TheChosenUndead": {
        "games": 22,
        "avg_damage": 93163.82,
        "avg_damage_taken": 21064.05,
        "avg_gold": 8752.64,
        "avg_farm": 137.41,
        "avg_vision": 17.5,
        "avg_turret_damage": 1098.55,
        "avg_kills": 4.05,
        "avg_deaths": 3.86,
        "avg_assists": 5.77,
        "avg_kill_participation": 36.98,
        "winrate": 54.55
      },
      "Nikken": {
        "games": 2,
        "avg_damage": 149569.0,
        "avg_damage_taken": 15085.5,
        "avg_gold": 13134.5,
        "avg_farm": 220.0,
        "avg_vision": 18.0,
        "avg_turret_damage": 4135.5,
        "avg_kills": 8.0,
        "avg_deaths": 1.5,
        "avg_assists": 16.0,
        "avg_kill_participation": 55.56,
        "winrate": 100.0
      },
      "En Vlc No F0II0": {
        "games": 4,
        "avg_damage": 123776.0,
        "avg_damage_taken": 23643.25,
        "avg_gold": 10244.25,
        "avg_farm": 190.5,
        "avg_vision": 16.75,
        "avg_turret_damage": 2417.75,
        "avg_kills": 3.5,
        "avg_deaths": 5.0,
        "avg_assists": 9.25,
        "avg_kill_participation": 34.06,
        "winrate": 50.0
      },
      "FUSHROHDAH": {
        "games": 25,
        "avg_damage": 150493.4,
        "avg_damage_taken": 18564.92,
        "avg_gold": 11389.76,
        "avg_farm": 202.88,
        "avg_vision": 16.84,
        "avg_turret_damage": 2832.16,
        "avg_kills": 4.72,
        "avg_deaths": 4.68,
        "avg_assists": 7.24,
        "avg_kill_participation": 40.22,
        "winrate": 52.0
      },
      "Kayki マ": {
        "games": 4,
        "avg_damage": 101853.5,
        "avg_damage_taken": 18902.5,
        "avg_gold": 8643.0,
        "avg_farm": 166.0,
        "avg_vision": 22.25,
        "avg_turret_damage": 1725.75,
        "avg_kills": 1.5,
        "avg_deaths": 6.75,
        "avg_assists": 4.25,
        "avg_kill_participation": 30.54,
        "winrate": 25.0
      },
      "Dexus": {
        "games": 3,
        "avg_damage": 108909.33,
        "avg_damage_taken": 25483.67,
        "avg_gold": 10866.67,
        "avg_farm": 169.0,
        "avg_vision": 20.67,
        "avg_turret_damage": 1322.67,
        "avg_kills": 5.33,
        "avg_deaths": 7.33,
        "avg_assists": 3.33,
        "avg_kill_participation": 28.69,
        "winrate": 0.0
      },
      "maibad": {
        "games": 16,
        "avg_damage": 153831.38,
        "avg_damage_taken": 22430.06,
        "avg_gold": 13089.44,
        "avg_farm": 204.25,
        "avg_vision": 18.88,
        "avg_turret_damage": 1884.81,
        "avg_kills": 7.38,
        "avg_deaths": 5.38,
        "avg_assists": 6.88,
        "avg_kill_participation": 53.04,
        "winrate": 37.5
      },
      "Däzzler": {
        "games": 2,
        "avg_damage": 185480.5,
        "avg_damage_taken": 24966.0,
        "avg_gold": 14266.0,
        "avg_farm": 219.0,
        "avg_vision": 14.0,
        "avg_turret_damage": 7007.5,
        "avg_kills": 9.0,
        "avg_deaths": 4.0,
        "avg_assists": 11.5,
        "avg_kill_participation": 56.56,
        "winrate": 50.0
      }
    },
    "BOTTOM": {
      "Bustamantefanboy": {
        "games": 43,
        "avg_damage": 186236.77,
        "avg_damage_taken": 23395.67,
        "avg_gold": 13938.84,
        "avg_farm": 221.86,
        "avg_vision": 14.05,
        "avg_turret_damage": 4251.09,
        "avg_kills": 8.3,
        "avg_deaths": 5.16,
        "avg_assists": 8.35,
        "avg_kill_participation": 52.24,
        "winrate": 51.16
      },
      "Joseph Joestar": {
        "games": 15,
        "avg_damage": 137483.4,
        "avg_damage_taken": 22834.8,
        "avg_gold": 11048.53,
        "avg_farm": 176.6,
        "avg_vision": 13.47,
        "avg_turret_damage": 2751.07,
        "avg_kills": 5.0,
        "avg_deaths": 5.73,
        "avg_assists": 8.4,
        "avg_kill_participation": 40.69,
        "winrate": 60.0
      },
      "TheChosenUndead": {
        "games": 18,
        "avg_damage": 117953.78,
        "avg_damage_taken": 16975.11,
        "avg_gold": 9953.39,
        "avg_farm": 167.56,
        "avg_vision": 15.28,
        "avg_turret_damage": 1260.39,
        "avg_kills": 4.11,
        "avg_deaths": 5.89,
        "avg_assists": 5.72,
        "avg_kill_participation": 42.71,
        "winrate": 22.22
      },
      "Banshee": {
        "games": 37,
        "avg_damage": 159668.86,
        "avg_damage_taken": 19794.46,
        "avg_gold": 12831.22,
        "avg_farm": 209.41,
        "avg_vision": 16.24,
        "avg_turret_damage": 4035.78,
        "avg_kills": 7.27,
        "avg_deaths": 5.38,
        "avg_assists": 7.65,
        "avg_kill_participation": 47.11,
        "winrate": 59.46
      },
      "Frieren": {
        "games": 48,
        "avg_damage": 178142.58,
        "avg_damage_taken": 21833.56,
        "avg_gold": 13473.42,
        "avg_farm": 205.67,
        "avg_vision": 21.77,
        "avg_turret_damage": 3785.38,
        "avg_kills": 9.31,
        "avg_deaths": 4.79,
        "avg_assists": 8.31,
        "avg_kill_participation": 56.21,
        "winrate": 52.08
      },
      "SN Bin": {
        "games": 53,
        "avg_damage": 188258.06,
        "avg_damage_taken": 22911.49,
        "avg_gold": 14542.58,
        "avg_farm": 218.13,
        "avg_vision": 15.34,
        "avg_turret_damage": 4775.3,
        "avg_kills": 10.21,
        "avg_deaths": 5.74,
        "avg_assists": 7.32,
        "avg_kill_participation": 58.18,
        "winrate": 52.83
      },
      "Kyoraku": {
        "games": 37,
        "avg_damage": 191974.22,
        "avg_damage_taken": 23056.16,
        "avg_gold": 13385.08,
        "avg_farm": 225.03,
        "avg_vision": 16.62,
        "avg_turret_damage": 5002.86,
        "avg_kills": 7.27,
        "avg_deaths": 5.59,
        "avg_assists": 6.59,
        "avg_kill_participation": 52.91,
        "winrate": 43.24
      },
      "En Vlc No F0II0": {
        "games": 2,
        "avg_damage": 104046.0,
        "avg_damage_taken": 20391.5,
        "avg_gold": 9803.5,
        "avg_farm": 184.0,
        "avg_vision": 16.0,
        "avg_turret_damage": 181.5,
        "avg_kills": 2.5,
        "avg_deaths": 6.0,
        "avg_assists": 4.0,
        "avg_kill_participation": 29.17,
        "winrate": 0.0
      },
      "FUSHROHDAH": {
        "games": 7,
        "avg_damage": 137408.0,
        "avg_damage_taken": 20025.0,
        "avg_gold": 11272.29,
        "avg_farm": 182.0,
        "avg_vision": 17.43,
        "avg_turret_damage": 3921.29,
        "avg_kills": 4.86,
        "avg_deaths": 7.29,
        "avg_assists": 8.71,
        "avg_kill_participation": 38.06,
        "winrate": 42.86
      },
      "Nikken": {
        "games": 5,
        "avg_damage": 133996.8,
        "avg_damage_taken": 13032.0,
        "avg_gold": 10028.6,
        "avg_farm": 174.2,
        "avg_vision": 12.4,
        "avg_turret_damage": 2286.2,
        "avg_kills": 4.6,
        "avg_deaths": 2.8,
        "avg_assists": 5.4,
        "avg_kill_participation": 33.16,
        "winrate": 60.0
      },
      "maibad": {
        "games": 9,
        "avg_damage": 160046.22,
        "avg_damage_taken": 22883.33,
        "avg_gold": 12986.89,
        "avg_farm": 202.33,
        "avg_vision": 14.22,
        "avg_turret_damage": 2834.0,
        "avg_kills": 8.78,
        "avg_deaths": 6.33,
        "avg_assists": 7.33,
        "avg_kill_participation": 50.39,
        "winrate": 33.33
      },
      "Dexus": {
        "games": 1,
        "avg_damage": 449195.0,
        "avg_damage_taken": 49498.0,
        "avg_gold": 25365.0,
        "avg_farm": 284.0,
        "avg_vision": 30.0,
        "avg_turret_damage": 6931.0,
        "avg_kills": 22.0,
        "avg_deaths": 13.0,
        "avg_assists": 17.0,
        "avg_kill_participation": 70.91,
        "winrate": 100.0
      },
      "Däzzler": {
        "games": 2,
        "avg_damage": 127057.5,
        "avg_damage_taken": 15011.5,
        "avg_gold": 9288.5,
        "avg_farm": 189.0,
        "avg_vision": 16.0,
        "avg_turret_damage": 897.0,
        "avg_kills": 2.0,
        "avg_deaths": 6.0,
        "avg_assists": 4.0,
        "avg_kill_participation": 48.21,
        "winrate": 0.0
      }
    },
    "UTILITY": {
      "Kyoraku": {
        "games": 24,
        "avg_damage": 32155.08,
        "avg_damage_taken": 25667.71,
        "avg_gold": 9156.88,
        "avg_farm": 33.17,
        "avg_vision": 67.38,
        "avg_turret_damage": 631.04,
        "avg_kills": 3.12,
        "avg_deaths": 6.21,
        "avg_assists": 16.79,
        "avg_kill_participation": 66.45,
        "winrate": 33.33
      },
      "ñoki": {
        "games": 4,
        "avg_damage": 46369.5,
        "avg_damage_taken": 16109.75,
        "avg_gold": 8149.0,
        "avg_farm": 33.5,
        "avg_vision": 44.5,
        "avg_turret_damage": 1922.0,
        "avg_kills": 3.0,
        "avg_deaths": 6.25,
        "avg_assists": 9.0,
        "avg_kill_participation": 49.73,
        "winrate": 75.0
      },
      "Banshee": {
        "games": 35,
        "avg_damage": 24979.49,
        "avg_damage_taken": 18698.31,
        "avg_gold": 7871.17,
        "avg_farm": 26.49,
        "avg_vision": 61.29,
        "avg_turret_damage": 562.89,
        "avg_kills": 1.57,
        "avg_deaths": 6.0,
        "avg_assists": 13.46,
        "avg_kill_participation": 56.23,
        "winrate": 42.86
      },
      "En Vlc No F0II0": {
        "games": 39,
        "avg_damage": 32066.69,
        "avg_damage_taken": 25336.36,
        "avg_gold": 8288.49,
        "avg_farm": 34.64,
        "avg_vision": 51.9,
        "avg_turret_damage": 1059.69,
        "avg_kills": 1.59,
        "avg_deaths": 6.51,
        "avg_assists": 13.49,
        "avg_kill_participation": 55.72,
        "winrate": 41.03
      },
      "Joseph Joestar": {
        "games": 16,
        "avg_damage": 24673.12,
        "avg_damage_taken": 22073.38,
        "avg_gold": 8248.81,
        "avg_farm": 28.12,
        "avg_vision": 60.31,
        "avg_turret_damage": 623.31,
        "avg_kills": 2.0,
        "avg_deaths": 6.62,
        "avg_assists": 15.25,
        "avg_kill_participation": 59.75,
        "winrate": 50.0
      },
      "TheChosenUndead": {
        "games": 78,
        "avg_damage": 22507.08,
        "avg_damage_taken": 23964.86,
        "avg_gold": 8826.77,
        "avg_farm": 24.5,
        "avg_vision": 71.54,
        "avg_turret_damage": 668.67,
        "avg_kills": 2.13,
        "avg_deaths": 6.82,
        "avg_assists": 17.35,
        "avg_kill_participation": 59.49,
        "winrate": 55.13
      },
      "Bustamantefanboy": {
        "games": 18,
        "avg_damage": 24169.28,
        "avg_damage_taken": 20041.33,
        "avg_gold": 8696.83,
        "avg_farm": 27.67,
        "avg_vision": 50.89,
        "avg_turret_damage": 1120.39,
        "avg_kills": 1.44,
        "avg_deaths": 5.28,
        "avg_assists": 17.11,
        "avg_kill_participation": 67.35,
        "winrate": 55.56
      },
      "Däzzler": {
        "games": 25,
        "avg_damage": 27745.12,
        "avg_damage_taken": 18743.24,
        "avg_gold": 8045.76,
        "avg_farm": 31.8,
        "avg_vision": 60.92,
        "avg_turret_damage": 907.84,
        "avg_kills": 1.96,
        "avg_deaths": 5.04,
        "avg_assists": 15.64,
        "avg_kill_participation": 57.92,
        "winrate": 60.0
      },
      "SN Bin": {
        "games": 8,
        "avg_damage": 41998.88,
        "avg_damage_taken": 25359.25,
        "avg_gold": 8892.0,
        "avg_farm": 34.62,
        "avg_vision": 64.38,
        "avg_turret_damage": 667.25,
        "avg_kills": 2.88,
        "avg_deaths": 6.12,
        "avg_assists": 15.88,
        "avg_kill_participation": 53.0,
        "winrate": 37.5
      },
      "Kayki マ": {
        "games": 2,
        "avg_damage": 23409.5,
        "avg_damage_taken": 25254.5,
        "avg_gold": 8469.0,
        "avg_farm": 24.5,
        "avg_vision": 55.5,
        "avg_turret_damage": 295.0,
        "avg_kills": 2.5,
        "avg_deaths": 8.0,
        "avg_assists": 9.5,
        "avg_kill_participation": 36.47,
        "winrate": 0.0
      },
      "FUSHROHDAH": {
        "games": 4,
        "avg_damage": 17419.25,
        "avg_damage_taken": 7841.75,
        "avg_gold": 4999.25,
        "avg_farm": 23.5,
        "avg_vision": 32.75,
        "avg_turret_damage": 463.25,
        "avg_kills": 0.25,
        "avg_deaths": 3.25,
        "avg_assists": 6.25,
        "avg_kill_participation": 39.32,
        "winrate": 50.0
      },
      "Frieren": {
        "games": 7,
        "avg_damage": 38058.29,
        "avg_damage_taken": 28831.71,
        "avg_gold": 10954.29,
        "avg_farm": 30.71,
        "avg_vision": 82.57,
        "avg_turret_damage": 695.0,
        "avg_kills": 3.29,
        "avg_deaths": 6.57,
        "avg_assists": 25.14,
        "avg_kill_participation": 68.76,
        "winrate": 71.43
      },
      "Nikken": {
        "games": 1,
        "avg_damage": 18837.0,
        "avg_damage_taken": 20898.0,
        "avg_gold": 7028.0,
        "avg_farm": 37.0,
        "avg_vision": 34.0,
        "avg_turret_damage": 160.0,
        "avg_kills": 3.0,
        "avg_deaths": 7.0,
        "avg_assists": 6.0,
        "avg_kill_participation": 60.0,
        "winrate": 0.0
      },
      "Morocha": {
        "games": 1,
        "avg_damage": 51253.0,
        "avg_damage_taken": 18017.0,
        "avg_gold": 8475.0,
        "avg_farm": 46.0,
        "avg_vision": 13.0,
        "avg_turret_damage": 3647.0,
        "avg_kills": 3.0,
        "avg_deaths": 2.0,
        "avg_assists": 21.0,
        "avg_kill_participation": 82.76,
        "winrate": 100.0
      },
      "maibad": {
        "games": 2,
        "avg_damage": 20513.5,
        "avg_damage_taken": 21772.5,
        "avg_gold": 7521.5,
        "avg_farm": 20.0,
        "avg_vision": 40.5,
        "avg_turret_damage": 493.5,
        "avg_kills": 1.0,
        "avg_deaths": 6.0,
        "avg_assists": 18.0,
        "avg_kill_participation": 69.44,
        "winrate": 50.0
      },
      "Lady Maria": {
        "games": 11,
        "avg_damage": 14146.09,
        "avg_damage_taken": 16174.09,
        "avg_gold": 7708.45,
        "avg_farm": 11.0,
        "avg_vision": 39.36,
        "avg_turret_damage": 1651.09,
        "avg_kills": 1.09,
        "avg_deaths": 6.18,
        "avg_assists": 13.64,
        "avg_kill_participation": 45.5,
        "winrate": 54.55
      },
      "Dexus": {
        "games": 2,
        "avg_damage": 19667.0,
        "avg_damage_taken": 12777.0,
        "avg_gold": 4910.0,
        "avg_farm": 26.5,
        "avg_vision": 19.5,
        "avg_turret_damage": 75.5,
        "avg_kills": 1.0,
        "avg_deaths": 5.5,
        "avg_assists": 2.5,
        "avg_kill_participation": 61.67,
        "winrate": 0.0
      }
    }
  }
}