{
  "source_L1": "L1_q440_min5_pool_ac89fa8d",
  "generated_at": "2025-12-02 03:00:59",
  "start_date": "2025-11-01",
  "end_date": "2025-12-01",
  "skills": {
    "Frieren": {
      "avg_Q": 131.42222222222222,
      "avg_W": 52.75555555555555,
      "avg_E": 62.46666666666667,
      "avg_R": 15.177777777777777,
      "max_Q": 584,
      "max_W": 119,
      "max_E": 292,
      "max_R": 56,
      "matches": 45
    },
    "Kyoraku": {
      "avg_Q": 119.78260869565217,
      "avg_W": 51.19565217391305,
      "avg_E": 67.1086956521739,
      "avg_R": 28.695652173913043,
      "max_Q": 393,
      "max_W": 228,
      "max_E": 237,
      "max_R": 274,
      "matches": 46
    },
    "Banshee": {
      "avg_Q": 105.52941176470588,
      "avg_W": 85.58823529411765,
      "avg_E": 49.588235294117645,
      "avg_R": 13.411764705882353,
      "max_Q": 266,
      "max_W": 256,
      "max_E": 204,
      "max_R": 50,
      "matches": 34
    },
    "Bustamantefanboy": {
      "avg_Q": 142.55102040816325,
      "avg_W": 65.20408163265306,
      "avg_E": 54.91836734693877,
      "avg_R": 9.306122448979592,
      "max_Q": 866,
      "max_W": 191,
      "max_E": 229,
      "max_R": 33,
      "matches": 49
    },
    "Dexus": {
      "avg_Q": 149.58139534883722,
      "avg_W": 55.06976744186046,
      "avg_E": 101.93023255813954,
      "avg_R": 20.511627906976745,
      "max_Q": 506,
      "max_W": 181,
      "max_E": 275,
      "max_R": 246,
      "matches": 43
    },
    "SN Bin": {
      "avg_Q": 81.33333333333333,
      "avg_W": 64.33333333333333,
      "avg_E": 54.666666666666664,
      "avg_R": 16.333333333333332,
      "max_Q": 126,
      "max_W": 79,
      "max_E": 136,
      "max_R": 30,
      "matches": 3
    },
    "Joseph Joestar": {
      "avg_Q": 123.02631578947368,
      "avg_W": 57.63157894736842,
      "avg_E": 62.76315789473684,
      "avg_R": 8.447368421052632,
      "max_Q": 295,
      "max_W": 241,
      "max_E": 157,
      "max_R": 40,
      "matches": 38
    },
    "TheChosenUndead": {
      "avg_Q": 109.475,
      "avg_W": 43.725,
      "avg_E": 77.3,
      "avg_R": 7.85,
      "max_Q": 336,
      "max_W": 95,
      "max_E": 277,
      "max_R": 16,
      "matches": 40
    },
    "Kayki マ": {
      "avg_Q": 79.96296296296296,
      "avg_W": 44.851851851851855,
      "avg_E": 36.111111111111114,
      "avg_R": 7.592592592592593,
      "max_Q": 175,
      "max_W": 166,
      "max_E": 122,
      "max_R": 29,
      "matches": 27
    },
    "En Vlc No F0II0": {
      "avg_Q": 74.4,
      "avg_W": 78.4,
      "avg_E": 52.5,
      "avg_R": 7.8,
      "max_Q": 113,
      "max_W": 305,
      "max_E": 126,
      "max_R": 12,
      "matches": 10
    },
    "Nikken": {
      "avg_Q": 209.0,
      "avg_W": 69.0,
      "avg_E": 79.0,
      "avg_R": 27.0,
      "max_Q": 209,
      "max_W": 69,
      "max_E": 79,
      "max_R": 27,
      "matches": 1
    },
    "Däzzler": {
      "avg_Q": 92.18181818181819,
      "avg_W": 59.72727272727273,
      "avg_E": 70.63636363636364,
      "avg_R": 15.181818181818182,
      "max_Q": 223,
      "max_W": 142,
      "max_E": 145,
      "max_R": 80,
      "matches": 11
    },
    "Morocha": {
      "avg_Q": 149.5,
      "avg_W": 45.25,
      "avg_E": 45.0,
      "avg_R": 6.5,
      "max_Q": 364,
      "max_W": 77,
      "max_E": 81,
      "max_R": 15,
      "matches": 4
    },
    "Lady Maria": {
      "avg_Q": 24.5,
      "avg_W": 47.5,
      "avg_E": 38.25,
      "avg_R": 6.75,
      "max_Q": 28,
      "max_W": 75,
      "max_E": 55,
      "max_R": 10,
      "matches": 4
    }
  }
}